fsearchpy/__init__.py
fsearchpy/fsearchpy.py
fsearchpy-0.4.dist-info/METADATA
fsearchpy-0.4.dist-info/WHEEL
fsearchpy-0.4.dist-info/entry_points.txt
fsearchpy-0.4.dist-info/top_level.txt
fsearchpy-0.4.dist-info/RECORD
